{"cameraMode":{"drawMode":0,"name":"Shaded","section":"Shading Mode"},"sceneLighting":false,"audioPlay":false,"sceneViewState":{"showFog":true,"showMaterialUpdate":false,"showSkybox":false,"showFlares":true,"showImageEffects":true,"showParticleSystems":true},"in2DMode":false,"pivot":{"x":9.173758506774903,"y":-2.6959292888641359,"z":5.512922286987305},"rotation":{"x":-0.1452099084854126,"y":-0.24165552854537965,"z":0.036584045737981799,"w":-0.9587599635124207},"size":5.630377769470215,"orthographic":false}